.flake8
.mailmap
LICENSE
MANIFEST.in
README.md
pyproject.toml
pytest.ini
setup.cfg
setup.py
docs/.gitignore
docs/Makefile
docs/PyMiner介绍.md
docs/THANKS
docs/make.bat
docs/make_doc.py
docs/upload.py
docs/source/conf.py
docs/source/contents.rst
docs/source/_static/.gitkeep
docs/source/_static/css/README.txt
docs/source/_static/css/pyminer.css
docs/source/_static/css/pyminer.css.map
docs/source/_static/css/pyminer.sass
docs/source/_static/index_files/all.css
docs/source/_static/index_files/all.js(1).download
docs/source/_static/index_files/all.js(2).download
docs/source/_static/index_files/all.js.download
docs/source/_static/index_files/check_data.png
docs/source/_static/index_files/code.png
docs/source/_static/index_files/font-awesome.min.css
docs/source/_static/index_files/ico_mailme_01.png
docs/source/_static/index_files/main.png
docs/source/_static/index_files/modernizr.js.download
docs/source/_static/index_files/normalize.css
docs/source/_static/index_files/robot.svg
docs/source/_templates/index.html
docs/source/contribute/index.md
examples/HereWeGo.py
examples/README.md
examples/README_ZH.md
examples/UCI_Credit_Card.csv
examples/woe_rule.pkl
examples/datasets/TitanicData.xls
examples/datasets/UCI_Credit_Card.csv
examples/datasets/air_quality_no2.csv
examples/datasets/bankloan.sav
examples/datasets/boston_house_prices.csv
examples/datasets/brown-selected.tab
examples/datasets/brown-selected.tab.metadata
examples/datasets/car_sales.sav
examples/datasets/cars.sas7bdat
examples/datasets/ccpp.csv
examples/datasets/class.sas7bdat
examples/datasets/conferences.dst
examples/datasets/datasets.info
examples/datasets/diabetes.csv
examples/datasets/heart_disease.tab
examples/datasets/heart_disease.tab.metadata
examples/datasets/housing.tab
examples/datasets/housing.tab.metadata
examples/datasets/iris.csv
examples/datasets/iris.tab
examples/datasets/iris.tab.metadata
examples/datasets/list_update.py
examples/datasets/mushrooms.csv
examples/datasets/slovenian-towns.dst
pyminer.egg-info/PKG-INFO
pyminer.egg-info/SOURCES.txt
pyminer.egg-info/dependency_links.txt
pyminer.egg-info/entry_points.txt
pyminer.egg-info/requires.txt
pyminer.egg-info/top_level.txt
