Metadata-Version: 2.1
Name: pyminer
Version: 2.1.2
Summary: pyminer, a component-based data mining framework.
Home-page: https://gitee.com/py2cn/pyminer
Author: pyminer development team
Author-email: team@pyminer.com
License: UNKNOWN
Project-URL: Bug Tracker, https://gitee.com/py2cn/pyminer/issues
Platform: UNKNOWN
Classifier: Programming Language :: Python :: 3
Classifier: License :: OSI Approved :: GNU Lesser General Public License v3 or later (LGPLv3+)
Classifier: Operating System :: POSIX
Classifier: Operating System :: Microsoft :: Windows
Classifier: Topic :: Scientific/Engineering :: Artificial Intelligence
Classifier: Topic :: Scientific/Engineering :: Visualization
Classifier: Intended Audience :: Science/Research
Classifier: Intended Audience :: Education
Requires-Python: >=3.7
License-File: LICENSE
